README.md
setup.py
hakuphi/__init__.py
hakuphi/attn_patcher.py
hakuphi/inference.py
hakuphi.egg-info/PKG-INFO
hakuphi.egg-info/SOURCES.txt
hakuphi.egg-info/dependency_links.txt
hakuphi.egg-info/not-zip-safe
hakuphi.egg-info/requires.txt
hakuphi.egg-info/top_level.txt
hakuphi/model/__init__.py
hakuphi/model/configuration_phi.py
hakuphi/model/configuration_phi_hf.py
hakuphi/model/modeling_phi.py
hakuphi/model/modeling_phi_hf.py
hakuphi/tools/__init__.py
hakuphi/tools/add_tokens.py
hakuphi/trainer/__init__.py
hakuphi/trainer/trainer.py
hakuphi/utils/__init__.py
hakuphi/utils/callbacks.py
hakuphi/utils/xformers_utils.py